imcp/__init__.py
imcp/main.py
tool_天气/__init__.py
tool_天气/tool1_get_jwt.py
tool_天气/tool2_get_city_info.py
tool_天气/tool3_get_now_weather.py
tool_天气/tool4_get_3_30day_weather.py
imcp_weather-0.1.6.dist-info/METADATA
imcp_weather-0.1.6.dist-info/WHEEL
imcp_weather-0.1.6.dist-info/entry_points.txt
imcp_weather-0.1.6.dist-info/top_level.txt
imcp_weather-0.1.6.dist-info/RECORD
