Metadata-Version: 2.4
Name: imcp-weather
Version: 0.1.6
Summary: 这是我自己的mcp工具集合(IMCP - Intelligent MCP)
Requires-Python: >=3.13
Requires-Dist: httpx>=0.28.1
Requires-Dist: mcp[cli]>=1.20.0
Requires-Dist: pyjwt
Requires-Dist: pytz>=2025.2
Provides-Extra: dev
Requires-Dist: build>=1.0.0; extra == "dev"
Requires-Dist: twine>=4.0.0; extra == "dev"
